datalibro_utils/__init__.py
datalibro_utils/datalibro_auth.py
datalibro_utils/dlbi.py
datalibro_utils/email.py
datalibro_utils/mapping.py
datalibro_utils/openai.py
datalibro_utils/pet_sys.py
datalibro_utils/test.py
datalibro_utils-2.3.10.dist-info/METADATA
datalibro_utils-2.3.10.dist-info/WHEEL
datalibro_utils-2.3.10.dist-info/top_level.txt
datalibro_utils-2.3.10.dist-info/RECORD
